{
  "event_id": "EV01132",
  "window": {
    "hourly_fvg_id": "FH06716",
    "hourly_start_time": "2021-12-23T11:00",
    "touch_window_hours": 3,
    "bos_window_hours": 3,
    "bos_window_start": "2021-12-23 13:30",
    "bos_window_end": "2021-12-23 16:30"
  },
  "hourly_fvg": {
    "fvg_hour_id": "FH06716",
    "direction": "up",
    "start_time": "2021-12-23T11:00",
    "begin_bound": 16183.75,
    "end_bound": 16189.75
  },
  "touch": {
    "touch_id": "TCH0050772",
    "fvg_hour_id": "FH06716",
    "fvg_direction": "up",
    "fvg_start_time": "2021-12-23T11:00",
    "window_start": "2021-12-23T12:00",
    "window_end": "2021-12-23T15:00",
    "ts_event": "2021-12-23 13:30",
    "price_touched": 16186.25,
    "bound_broken": 16189.75,
    "touch_type": "touch_up_fvg"
  },
  "fvg_5m_in_window": [
    {
      "fvg_5m_id": "F5165618",
      "direction": "up",
      "start_time": "2021-12-23T14:00",
      "begin_bound": 16192.0,
      "end_bound": 16193.75,
      "index_first_touch": 3,
      "index_valid_close_after_touch": 4
    },
    {
      "fvg_5m_id": "F5165619",
      "direction": "up",
      "start_time": "2021-12-23T14:05",
      "begin_bound": 16196.25,
      "end_bound": 16197.75,
      "index_first_touch": 1,
      "index_valid_close_after_touch": 3
    }
  ],
  "bos_5m_in_window": [
    {
      "bos_id": "BOS0121009",
      "ts_event": "2021-12-23 13:40",
      "bos_direction": "bos_down",
      "trigger_close": 16175.75,
      "broken_level": 16190.5,
      "source_hilo_id": "HL0807899"
    },
    {
      "bos_id": "BOS0121010",
      "ts_event": "2021-12-23 14:00",
      "bos_direction": "bos_up",
      "trigger_close": 16203.25,
      "broken_level": 16201.0,
      "source_hilo_id": "HL0807900"
    },
    {
      "bos_id": "BOS0121011",
      "ts_event": "2021-12-23 14:25",
      "bos_direction": "bos_down",
      "trigger_close": 16184.25,
      "broken_level": 16188.75,
      "source_hilo_id": "HL0807910"
    },
    {
      "bos_id": "BOS0121012",
      "ts_event": "2021-12-23 14:30",
      "bos_direction": "bos_up",
      "trigger_close": 16211.0,
      "broken_level": 16200.25,
      "source_hilo_id": "HL0807911"
    },
    {
      "bos_id": "BOS0121013",
      "ts_event": "2021-12-23 15:10",
      "bos_direction": "bos_up",
      "trigger_close": 16258.5,
      "broken_level": 16253.25,
      "source_hilo_id": "HL0807918"
    },
    {
      "bos_id": "BOS0121014",
      "ts_event": "2021-12-23 15:45",
      "bos_direction": "bos_up",
      "trigger_close": 16277.5,
      "broken_level": 16272.75,
      "source_hilo_id": "HL0807923"
    }
  ],
  "trade_signals": [
    {
      "signal": "buy_long",
      "fvg_5m_id": "F5165618",
      "direction": "up",
      "index_first_touch": 3,
      "index_valid_close_after_touch": 4,
      "entry_ts": "2021-12-23 14:20",
      "entry_price": 16199.75,
      "stop_loss": 16169.5,
      "take_profit": 16230.0,
      "exit_signal": "sell_l_prof",
      "exit_ts": "2021-12-23 14:35",
      "exit_price": 16230.0
    }
  ],
  "summary": {
    "count_fvg_5m": 2,
    "count_bos_5m": 6,
    "count_signals": 1
  }
}