{
  "event_id": "EV01326",
  "window": {
    "hourly_fvg_id": "FH07921",
    "hourly_start_time": "2023-12-22T14:00",
    "touch_window_hours": 3,
    "bos_window_hours": 3,
    "bos_window_start": "2023-12-22 16:00",
    "bos_window_end": "2023-12-22 19:00"
  },
  "hourly_fvg": {
    "fvg_hour_id": "FH07921",
    "direction": "up",
    "start_time": "2023-12-22T14:00",
    "begin_bound": 16952.25,
    "end_bound": 16989.25
  },
  "touch": {
    "touch_id": "TCH0059358",
    "fvg_hour_id": "FH07921",
    "fvg_direction": "up",
    "fvg_start_time": "2023-12-22T14:00",
    "window_start": "2023-12-22T15:00",
    "window_end": "2023-12-22T18:00",
    "ts_event": "2023-12-22 16:00",
    "price_touched": 16970.0,
    "bound_broken": 16989.25,
    "touch_type": "touch_up_fvg"
  },
  "fvg_5m_in_window": [
    {
      "fvg_5m_id": "F5194116",
      "direction": "up",
      "start_time": "2023-12-22T17:45",
      "begin_bound": 17000.0,
      "end_bound": 17000.5,
      "index_first_touch": 1,
      "index_valid_close_after_touch": 1
    }
  ],
  "bos_5m_in_window": [
    {
      "bos_id": "BOS0144942",
      "ts_event": "2023-12-22 16:30",
      "bos_direction": "bos_up",
      "trigger_close": 17005.25,
      "broken_level": 17002.75,
      "source_hilo_id": "HL0949725"
    },
    {
      "bos_id": "BOS0144943",
      "ts_event": "2023-12-22 17:10",
      "bos_direction": "bos_down",
      "trigger_close": 16977.0,
      "broken_level": 16982.25,
      "source_hilo_id": "HL0949732"
    },
    {
      "bos_id": "BOS0144944",
      "ts_event": "2023-12-22 17:25",
      "bos_direction": "bos_up",
      "trigger_close": 16989.75,
      "broken_level": 16987.0,
      "source_hilo_id": "HL0949738"
    },
    {
      "bos_id": "BOS0144945",
      "ts_event": "2023-12-22 17:35",
      "bos_direction": "bos_up",
      "trigger_close": 16999.75,
      "broken_level": 16993.75,
      "source_hilo_id": "HL0949740"
    },
    {
      "bos_id": "BOS0144946",
      "ts_event": "2023-12-22 18:05",
      "bos_direction": "bos_up",
      "trigger_close": 17012.25,
      "broken_level": 17010.0,
      "source_hilo_id": "HL0949743"
    },
    {
      "bos_id": "BOS0144947",
      "ts_event": "2023-12-22 18:50",
      "bos_direction": "bos_down",
      "trigger_close": 17010.0,
      "broken_level": 17012.0,
      "source_hilo_id": "HL0949752"
    }
  ],
  "trade_signals": [
    {
      "signal": "buy_long",
      "fvg_5m_id": "F5194116",
      "direction": "up",
      "index_first_touch": 1,
      "index_valid_close_after_touch": 1,
      "entry_ts": "2023-12-22 17:50",
      "entry_price": 17005.25,
      "stop_loss": 16967.25,
      "take_profit": 17043.25,
      "exit_signal": "sell_l_loss",
      "exit_ts": "2023-12-22 19:05",
      "exit_price": 16967.25
    }
  ],
  "summary": {
    "count_fvg_5m": 1,
    "count_bos_5m": 6,
    "count_signals": 1
  }
}