{
  "event_id": "EV01477",
  "window": {
    "hourly_fvg_id": "FH08823",
    "hourly_start_time": "2025-06-26T19:00",
    "touch_window_hours": 3,
    "bos_window_hours": 3,
    "bos_window_start": "2025-06-26 20:00",
    "bos_window_end": "2025-06-26 23:00"
  },
  "hourly_fvg": {
    "fvg_hour_id": "FH08823",
    "direction": "up",
    "start_time": "2025-06-26T19:00",
    "begin_bound": 22652.0,
    "end_bound": 22652.5
  },
  "touch": {
    "touch_id": "TCH0065432",
    "fvg_hour_id": "FH08823",
    "fvg_direction": "up",
    "fvg_start_time": "2025-06-26T19:00",
    "window_start": "2025-06-26T20:00",
    "window_end": "2025-06-26T23:00",
    "ts_event": "2025-06-26 20:00",
    "price_touched": 22641.0,
    "bound_broken": 22652.5,
    "touch_type": "touch_up_fvg"
  },
  "fvg_5m_in_window": [
    {
      "fvg_5m_id": "F5215323",
      "direction": "up",
      "start_time": "2025-06-26T20:25",
      "begin_bound": 22662.25,
      "end_bound": 22665.0,
      "index_first_touch": 1,
      "index_valid_close_after_touch": 1
    },
    {
      "fvg_5m_id": "F5215324",
      "direction": "up",
      "start_time": "2025-06-26T20:35",
      "begin_bound": 22670.5,
      "end_bound": 22672.75,
      "index_first_touch": 1,
      "index_valid_close_after_touch": 5
    }
  ],
  "bos_5m_in_window": [
    {
      "bos_id": "BOS0162702",
      "ts_event": "2025-06-26 20:00",
      "bos_direction": "bos_down",
      "trigger_close": 22649.25,
      "broken_level": 22653.75,
      "source_hilo_id": "HL1056114"
    },
    {
      "bos_id": "BOS0162703",
      "ts_event": "2025-06-26 20:15",
      "bos_direction": "bos_up",
      "trigger_close": 22662.0,
      "broken_level": 22661.0,
      "source_hilo_id": "HL1056119"
    },
    {
      "bos_id": "BOS0162704",
      "ts_event": "2025-06-26 20:30",
      "bos_direction": "bos_up",
      "trigger_close": 22673.75,
      "broken_level": 22672.5,
      "source_hilo_id": "HL1056122"
    },
    {
      "bos_id": "BOS0162705",
      "ts_event": "2025-06-26 22:00",
      "bos_direction": "bos_up",
      "trigger_close": 22682.25,
      "broken_level": 22677.0,
      "source_hilo_id": "HL1056125"
    },
    {
      "bos_id": "BOS0162706",
      "ts_event": "2025-06-26 22:25",
      "bos_direction": "bos_up",
      "trigger_close": 22701.0,
      "broken_level": 22698.0,
      "source_hilo_id": "HL1056131"
    },
    {
      "bos_id": "BOS0162707",
      "ts_event": "2025-06-26 22:40",
      "bos_direction": "bos_down",
      "trigger_close": 22695.25,
      "broken_level": 22695.75,
      "source_hilo_id": "HL1056136"
    }
  ],
  "trade_signals": [
    {
      "signal": "buy_long",
      "fvg_5m_id": "F5215323",
      "direction": "up",
      "index_first_touch": 1,
      "index_valid_close_after_touch": 1,
      "entry_ts": "2025-06-26 20:30",
      "entry_price": 22673.75,
      "stop_loss": 22640.25,
      "take_profit": 22707.25,
      "exit_signal": "sell_l_loss_session_close",
      "exit_ts": "2025-06-26 20:55",
      "exit_price": 22672.5
    }
  ],
  "summary": {
    "count_fvg_5m": 2,
    "count_bos_5m": 6,
    "count_signals": 1
  }
}